strtest/__init__.py
strtest/mock_import.py
strtest/str_test.py
strtest-0.1.0.data/scripts/run_str_test.py
strtest-0.1.0.dist-info/LICENSE
strtest-0.1.0.dist-info/METADATA
strtest-0.1.0.dist-info/WHEEL
strtest-0.1.0.dist-info/top_level.txt
strtest-0.1.0.dist-info/RECORD
