Metadata-Version: 2.1
Name: strtest
Version: 0.1.0
Summary: Runs test code contained in strings
Home-page: https://github.com/Insper/python-string-test-runner
Author: Andrew Kurauchi
Author-email: andrewtnk@insper.edu.br
License: MIT
Platform: UNKNOWN
Classifier: License :: OSI Approved :: MIT License
Classifier: Programming Language :: Python :: 3
Classifier: Programming Language :: Python :: 3.7
